cipher_yb2503/__init__.py
cipher_yb2503/cipher_yb2503.py
cipher_yb2503-0.1.1.dist-info/LICENSE
cipher_yb2503-0.1.1.dist-info/WHEEL
cipher_yb2503-0.1.1.dist-info/METADATA
cipher_yb2503-0.1.1.dist-info/RECORD
