Metadata-Version: 2.1
Name: cipher-yb2503
Version: 0.1.1
Summary: We are adding cipher to the package
Home-page: https://github.com/QMSS-G5072-2021/cipher_bo_yunxin
License: MIT
Author: Yunxin Bo
Requires-Python: >=3.8,<4.0
Classifier: License :: OSI Approved :: MIT License
Classifier: Programming Language :: Python :: 3
Classifier: Programming Language :: Python :: 3.8
Classifier: Programming Language :: Python :: 3.9
Project-URL: Repository, https://github.com/QMSS-G5072-2021/cipher_bo_yunxin
